upper_lower_lib/__init__.py
upper_lower_lib/__main__.py
upper_lower_lib/core.py
upperlowerlib-0.1.0.dist-info/licenses/LICENSE
upperlowerlib-0.1.0.dist-info/METADATA
upperlowerlib-0.1.0.dist-info/WHEEL
upperlowerlib-0.1.0.dist-info/entry_points.txt
upperlowerlib-0.1.0.dist-info/top_level.txt
upperlowerlib-0.1.0.dist-info/RECORD
