Metadata-Version: 2.4
Name: UpperLowerLib
Version: 0.1.0
Summary: Convert text to upper or lower case
Author: Amal Ahmed Mohammed Al-Sharif
Author-email: Amal Ahmed Mohammed Al-Sharif <alsharif5433@gmail.com>
License: MIT License
Requires-Python: >=3.7
License-File: LICENSE
Dynamic: author
Dynamic: license-file
Dynamic: requires-python
